loanpred/DecisionTree.py
loanpred/LogisticRegression.py
loanpred/__init__.py
loanpred-0.0.7.dist-info/METADATA
loanpred-0.0.7.dist-info/WHEEL
loanpred-0.0.7.dist-info/licenses/LICENSE
loanpred-0.0.7.dist-info/RECORD
