Metadata-Version: 2.1
Name: loanpred
Version: 0.0.7
Summary: Machine Learning for loanpred
Author-email: ananya kumar dhal <ananyakumardhal2003@gmail.com>
License: Copyright (c) 2022 ANANYA
License-File: LICENSE
Classifier: License :: OSI Approved :: MIT License
Classifier: Operating System :: OS Independent
Classifier: Programming Language :: Python :: 3
Requires-Python: >=3.7
